{
  "제목": "초밥 덕후들을 설레게 할 화려한 스시롤 만들기♡",
  "설명": "겉모습에 한번 맛에 두번 놀라는 스시롤~",
  "serving": "2인분",
  "조리시간": "30분 이내",
  "난이도": "중급",
  "재료": {
    "필수재료": [
      {"이름": "밥", "양": "2그릇"},
      {"이름": "초밥용 식초", "양": "적당량"},
      {"이름": "후리카케", "양": "적당량"},
      {"이름": "김", "양": "1장"},
      {"이름": "차조기 잎", "양": "3장"},
      {"이름": "달걀 지단", "양": "1개"},
      {"이름": "날치알", "양": "적당량"},
      {"이름": "오이", "양": "1개", "설명": "얇게 썬 것"},
      {"이름": "스모크 살몬", "양": "적당량"}
    ]
  },
  "조리도구": [
    "김발",
    "랩",
    "칼",
    "도마",
    "접시"
  ],
  "조리순서": [
    {
      "단계": 1,
      "설명": "초밥을 4 가지로 나누어 각각 다른 색상의 후리카케를 섞어 밥에 색을 넣는다."
    },
    {
      "단계": 2,
      "설명": "김발 위에 아래 준비한 용지와 랩을 놓고 용지의 선에 맞추어 1을 좋아하는 곳에 놓는다.",
      "팁": "초밥 식초에 적신 숟가락으로 밥을 덜으면 밥이 눌러 붙지 않습니다."
    },
    {
      "단계": 3,
      "설명": "2 위에 김을 놓고 차조기 잎, 계란지단, 날치알, 오이, 훈제 연어 등 좋아하는 재료를 놓고 랩 째로 만다."
    },
    {
      "단계": 4,
      "설명": "원하는 두께로 썰어 접시에 담으면 완성입니다 ♪"
    }
  ],
  "팁": "[미리 준비할 것]\n밥, 초밥용 식초를 섞어 식혀 둔다.\n김과 같은 크기의 종이를 준비하여 4cm 간격으로 비스듬하게 선을 긋는다."
}